README.md
setup.cfg
setup.py
distributions_renatosfmedeiros/Binomialdistribution.py
distributions_renatosfmedeiros/Gaussiandistribution.py
distributions_renatosfmedeiros/Generaldistribution.py
distributions_renatosfmedeiros/__init__.py
distributions_renatosfmedeiros.egg-info/PKG-INFO
distributions_renatosfmedeiros.egg-info/SOURCES.txt
distributions_renatosfmedeiros.egg-info/dependency_links.txt
distributions_renatosfmedeiros.egg-info/not-zip-safe
distributions_renatosfmedeiros.egg-info/top_level.txt